Workbook
Name Slicer_Category1: #N/A
Name Slicer_Fulfillment: #N/A
Name Slicer_Order_Status1: #N/A

Sheet Sheet1
A1: Order_ID | B1: Order_Date | C1: Order month | D1: Category | E1: Product | F1: Quantity | G1: Unit_Price_INR | H1: Discount_Pct | I1: Total_Sales_INR | J1: Profit_INR | K1: Payment_Method | L1: Fulfillment | M1: Order_Status | N1: Ship_State
A2: IN-AMD-100000 | B2: 2024-04-12 | C2: =DATE(YEAR(B2),MONTH(B2),1) -> 45383 | D2: Apparel & Fashion | E2: Saree with Unstitched Blouse | F2: 3 | G2: 1129.14 | H2: 0.25 | I2: 2540.56 | J2: 702.96 | K2: Cash on Delivery (COD) | L2: Seller Flex | M2: Delivered | N2: Telangana
A3: IN-AMD-100001 | B3: 2025-03-11 | C3: =DATE(YEAR(B3),MONTH(B3),1) -> 45717 | D3: Apparel & Fashion | E3: Men Denim Jeans | F3: 3 | G3: 1159.01 | H3: 0.05 | I3: 3303.18 | J3: 770.96 | K3: UPI | L3: Amazon (FBA) | M3: Shipped | N3: Kerala
A4: IN-AMD-100002 | B4: 2026-05-10 | C4: =DATE(YEAR(B4),MONTH(B4),1) -> 46143 | D4: Beauty & Personal Care | E4: Ubtan Face Wash | F4: 1 | G4: 287.77 | H4: 0 | I4: 287.77 | J4: 86.73 | K4: UPI | L4: Amazon (FBA) | M4: Delivered | N4: West Bengal
A5: IN-AMD-100003 | B5: 2024-09-27 | C5: =DATE(YEAR(B5),MONTH(B5),1) -> 45536 | D5: Electronics & Mobiles | E5: Wireless Earbuds | F5: 4 | G5: 20928.14 | H5: 0.05 | I5: 79526.93 | J5: 26466.63 | K5: Credit/Debit Card | L5: Amazon (FBA) | M5: Shipped | N5: Rajasthan
A6: IN-AMD-100004 | B6: 2024-04-16 | C6: =DATE(YEAR(B6),MONTH(B6),1) -> 45383 | D6: Beauty & Personal Care | E6: Sunscreen Gel SPF 50 | F6: 1 | G6: 931.65 | H6: 0.15 | I6: 791.9 | J6: 217.9 | K6: UPI | L6: Seller Flex | M6: Delivered | N6: Karnataka
A7: IN-AMD-100005 | B7: 2024-03-12 | C7: =DATE(YEAR(B7),MONTH(B7),1) -> 45352 | D7: Home & Kitchen | E7: Cotton Bedsheet Double | F7: 1 | G7: 6953.38 | H7: 0.05 | I7: 6605.71 | J7: 2178.46 | K7: UPI | L7: Merchant (FBM) | M7: Delivered | N7: Kerala
A8: IN-AMD-100006 | B8: 2025-12-01 | C8: =DATE(YEAR(B8),MONTH(B8),1) -> 45992 | D8: Electronics & Mobiles | E8: Laptop Backpack | F8: 4 | G8: 10571.26 | H8: 0 | I8: 42285.04 | J8: 5342.57 | K8: Cash on Delivery (COD) | L8: Seller Flex | M8: Delivered | N8: Rajasthan
A9: IN-AMD-100007 | B9: 2024-01-21 | C9: =DATE(YEAR(B9),MONTH(B9),1) -> 45292 | D9: Pantry & Groceries | E9: Assorted Dry Fruits 500g | F9: 3 | G9: 1139.54 | H9: 0.1 | I9: 3076.76 | J9: 749.52 | K9: UPI | L9: Amazon (FBA) | M9: Delivered | N9: Kerala
A10: IN-AMD-100008 | B10: 2025-09-06 | C10: =DATE(YEAR(B10),MONTH(B10),1) -> 45901 | D10: Apparel & Fashion | E10: Sports Shoes | F10: 3 | G10: 1316.95 | H10: 0 | I10: 3950.85 | J10: 716.74 | K10: UPI | L10: Amazon (FBA) | M10: Delivered | N10: Maharashtra
A11: IN-AMD-100009 | B11: 2024-05-01 | C11: =DATE(YEAR(B11),MONTH(B11),1) -> 45413 | D11: Electronics & Mobiles | E11: Laptop Backpack | F11: 2 | G11: 16568.45 | H11: 0 | I11: 33136.9 | J11: 0 | K11: Credit/Debit Card | L11: Merchant (FBM) | M11: Returned | N11: Kerala | P11: Monthly Sales & Profit Trends
A12: IN-AMD-100010 | B12: 2025-04-11 | C12: =DATE(YEAR(B12),MONTH(B12),1) -> 45748 | D12: Apparel & Fashion | E12: Men Denim Jeans | F12: 4 | G12: 2874.25 | H12: 0 | I12: 11497 | J12: 2120.88 | K12: UPI | L12: Amazon (FBA) | M12: Delivered | N12: Telangana
A13: IN-AMD-100011 | B13: 2024-08-02 | C13: =DATE(YEAR(B13),MONTH(B13),1) -> 45505 | D13: Beauty & Personal Care | E13: Ubtan Face Wash | F13: 1 | G13: 935.43 | H13: 0.15 | I13: 795.12 | J13: 245.28 | K13: UPI | L13: Amazon (FBA) | M13: Delivered | N13: Delhi
A14: IN-AMD-100012 | B14: 2024-11-26 | C14: =DATE(YEAR(B14),MONTH(B14),1) -> 45597 | D14: Apparel & Fashion | E14: Sports Shoes | F14: 4 | G14: 2602.61 | H14: 0.2 | I14: 8328.35 | J14: 2205.99 | K14: Credit/Debit Card | L14: Seller Flex | M14: Delivered | N14: Delhi
A15: IN-AMD-100013 | B15: 2025-04-03 | C15: =DATE(YEAR(B15),MONTH(B15),1) -> 45748 | D15: Electronics & Mobiles | E15: 5G Smartphone | F15: 1 | G15: 34141.47 | H15: 0.1 | I15: 30727.32 | J15: 9179.44 | K15: Credit/Debit Card | L15: Merchant (FBM) | M15: Shipped | N15: Maharashtra
A16: IN-AMD-100014 | B16: 2024-03-28 | C16: =DATE(YEAR(B16),MONTH(B16),1) -> 45352 | D16: Electronics & Mobiles | E16: Smartwatch | F16: 2 | G16: 4785.81 | H16: 0.05 | I16: 9093.04 | J16: 2136.51 | K16: UPI | L16: Amazon (FBA) | M16: Delivered | N16: Delhi
A17: IN-AMD-100015 | B17: 2025-01-07 | C17: =DATE(YEAR(B17),MONTH(B17),1) -> 45658 | D17: Electronics & Mobiles | E17: Power Bank 20000mAh | F17: 2 | G17: 27239.02 | H17: 0.05 | I17: 51754.14 | J17: 9391.35 | K17: UPI | L17: Amazon (FBA) | M17: Delivered | N17: Karnataka
A18: IN-AMD-100016 | B18: 2024-04-09 | C18: =DATE(YEAR(B18),MONTH(B18),1) -> 45383 | D18: Beauty & Personal Care | E18: Sunscreen Gel SPF 50 | F18: 2 | G18: 877.76 | H18: 0 | I18: 1755.52 | J18: 399.7 | K18: Credit/Debit Card | L18: Amazon (FBA) | M18: Shipped | N18: Telangana
A19: IN-AMD-100017 | B19: 2026-05-21 | C19: =DATE(YEAR(B19),MONTH(B19),1) -> 46143 | D19: Apparel & Fashion | E19: Men Denim Jeans | F19: 2 | G19: 2906.9 | H19: 0.2 | I19: 4651.04 | J19: 787.91 | K19: UPI | L19: Merchant (FBM) | M19: Delivered | N19: Tamil Nadu
A20: IN-AMD-100018 | B20: 2025-10-25 | C20: =DATE(YEAR(B20),MONTH(B20),1) -> 45931 | D20: Electronics & Mobiles | E20: Power Bank 20000mAh | F20: 1 | G20: 3336.61 | H20: 0.1 | I20: 3002.95 | J20: 1045.12 | K20: Credit/Debit Card | L20: Amazon (FBA) | M20: Shipped | N20: Kerala
A21: IN-AMD-100019 | B21: 2024-05-10 | C21: =DATE(YEAR(B21),MONTH(B21),1) -> 45413 | D21: Electronics & Mobiles | E21: Smartwatch | F21: 3 | G21: 13615.48 | H21: 0 | I21: 40846.44 | J21: 12164.43 | K21: UPI | L21: Merchant (FBM) | M21: Delivered | N21: Uttar Pradesh
A22: IN-AMD-100020 | B22: 2025-10-23 | C22: =DATE(YEAR(B22),MONTH(B22),1) -> 45931 | D22: Apparel & Fashion | E22: Saree with Unstitched Blouse | F22: 1 | G22: 1375.81 | H22: 0.05 | I22: 1307.02 | J22: 175.6 | K22: UPI | L22: Amazon (FBA) | M22: Delivered | N22: West Bengal
A23: IN-AMD-100021 | B23: 2024-11-04 | C23: =DATE(YEAR(B23),MONTH(B23),1) -> 45597 | D23: Pantry & Groceries | E23: Organic Turmeric Powder | F23: 2 | G23: 993.64 | H23: 0.1 | I23: 1788.55 | J23: 625.14 | K23: UPI | L23: Merchant (FBM) | M23: Delivered | N23: West Bengal
... A10001: IN-AMD-109999 | B10001: 2025-08-10 | C10001: =DATE(YEAR(B10001),MONTH(B10001),1) -> 45870 | D10001: Beauty & Personal Care | E10001: Matte Lipstick | F10001: 4 | G10001: 585.22 | H10001: 0.2 | I10001: 1872.7 | J10001: 510.26 | K10001: Credit/Debit Card | L10001: Amazon (FBA) | M10001: Delivered | N10001: Maharashtra

Sheet Sheet2
A3: Row Labels | B3: Sum of Total_Sales_INR
A4: Smartwatch | B4: 23312463
A5: Wireless Earbuds | B5: 23848641 | G5: Total Sales | H5: =SUM(Sheet1!I2:I10001) -> 1.5578989e+08
A6: 5G Smartphone | B6: 24330766 | G6: Total Profit | H6: =SUM(Sheet1!J2:J10001) -> 33167008
A7: Power Bank 20000mAh | B7: 25548449 | G7: Total Orders | H7: =COUNTA(Sheet1!A2:A10001) -> 10000
A8: Laptop Backpack | B8: 26529187 | G8: Total Unit Sold | H8: =SUM(Sheet1!F2:F10001) -> 24926
A9: Grand Total | B9: 1.2356951e+08 | G9: Average Order Values | H9: =IFERROR(H5/H7,0) -> 15578.989
F10: obj1 | G10: Profit Margin% | H10: =H6/H5 -> 0.21289576

Sheet Sheet3
A3: Order Date | B3: Sum of Total_Sales_INR
A4: Jan | B4: 13954653
A5: Feb | B5: 12707360
A6: Mar | B6: 15813226
A7: Apr | B7: 13695894
A8: May | B8: 14845666
A9: Jun | B9: 15269144
A10: Jul | B10: 17736471
A11: Aug | B11: 14649797
A12: Sep | B12: 8679665.8
A13: Oct | B13: 9607831
A14: Nov | B14: 9593588.6
A15: Dec | B15: 9236596.5
A16: Grand Total | B16: 1.5578989e+08

Sheet Sheet4
A3: Category | B3: Sum of Total_Sales_INR
A4: Electronics & Mobiles | B4: 1.2356951e+08
A5: Home & Kitchen | B5: 17973219
A6: Apparel & Fashion | B6: 9831025.1 | L6: Cancillation Rate %
A7: Beauty & Personal Care | B7: 2889178.5 | L7: 0.05
A8: Pantry & Groceries | B8: 1526964.3
A9: Grand Total | B9: 1.5578989e+08
A19: Category | B19: Sum of Profit_INR
A20: Pantry & Groceries | B20: 329738.48
A21: Beauty & Personal Care | B21: 604390.41
A22: Apparel & Fashion | B22: 2085354
A23: Home & Kitchen | B23: 3837268.4
A24: Electronics & Mobiles | B24: 26310257
A25: Grand Total | B25: 33167008
A37: Category | B37: Sum of Unit_Price_INR
A38: Apparel & Fashion | B38: 4315943.9
A39: Beauty & Personal Care | B39: 1273061.3
A40: Electronics & Mobiles | B40: 54002873
A41: Home & Kitchen | B41: 7957698
A42: Pantry & Groceries | B42: 664420.52
A43: Grand Total | B43: 68213997

Sheet Sheet5
A3: Row Labels | B3: Count of Total_Sales_INR
A4: Cancelled | B4: 500
A5: Delivered | B5: 8147
A6: Returned | B6: 485
A7: Shipped | B7: 868
A8: Grand Total | B8: 10000
B16: Return Orders | C16: =COUNTIF(Sheet1!M1:M10001,"Returned") -> 485
B17: Return Rate % | C17: =IFERROR(485/10000,0) -> 0.0485
B18: Cancellation Rate % | C18: =IFERROR(500/10000,0) -> 0.05
A21: Count of Order_ID | B21: Column Labels
A22: Row Labels | B22: Cancelled | C22: Delivered | D22: Returned | E22: Shipped | F22: Grand Total
A23: Apparel & Fashion | B23: 148 | C23: 2101 | D23: 110 | E23: 221 | F23: 2580
A24: Beauty & Personal Care | B24: 84 | C24: 1214 | D24: 75 | E24: 126 | F24: 1499
A25: Electronics & Mobiles | B25: 136 | C25: 2465 | D25: 164 | E25: 280 | F25: 3045
A26: Home & Kitchen | B26: 91 | C26: 1554 | D26: 90 | E26: 153 | F26: 1888
A27: Pantry & Groceries | B27: 41 | C27: 813 | D27: 46 | E27: 88 | F27: 988
A28: Grand Total | B28: 500 | C28: 8147 | D28: 485 | E28: 868 | F28: 10000

Sheet Sheet6
A3: Row Labels | B3: Sum of Total_Sales_INR | C3: Sum of Profit_INR
A4: Apparel & Fashion | B4: 9831025.1 | C4: 2085354
A5: Beauty & Personal Care | B5: 2889178.5 | C5: 604390.41
A6: Electronics & Mobiles | B6: 1.2356951e+08 | C6: 26310257
A7: Home & Kitchen | B7: 17973219 | C7: 3837268.4
A8: Pantry & Groceries | B8: 1526964.3 | C8: 329738.48
A9: Grand Total | B9: 1.5578989e+08 | C9: 33167008

Sheet Sheet7
A3: Payment_Method | B3: Sum of Total_Sales_INR
A4: Amazon Pay Later | B4: 7684156.6
A5: Cash on Delivery (COD) | B5: 23101584
A6: Credit/Debit Card | B6: 31069231
A7: Net Banking | B7: 15419486
A8: UPI | B8: 78515436
A9: Grand Total | B9: 1.5578989e+08
A14: Fullfillment | B14: Sum of Total_Sales_INR
A15: Amazon (FBA) | B15: 1.0752829e+08
A16: Merchant (FBM) | B16: 17063214
A17: Seller Flex | B17: 31198392
A18: Grand Total | B18: 1.5578989e+08
A21: State | B21: Count of Order_ID
A22: Delhi | B22: 1444
A23: Gujarat | B23: 591
A24: Karnataka | B24: 1515
A25: Kerala | B25: 483
A26: Maharashtra | B26: 1840
A27: Rajasthan | B27: 456
A28: Tamil Nadu | B28: 1109
A29: Telangana | B29: 906
A30: Uttar Pradesh | B30: 991
A31: West Bengal | B31: 665
A32: Grand Total | B32: 10000
A39: Fullfillment | B39: Count of Order_ID
A40: Delhi | B40: 1444
A41: Gujarat | B41: 591
A42: Karnataka | B42: 1515
A43: Kerala | B43: 483
A44: Maharashtra | B44: 1840
A45: Rajasthan | B45: 456
A46: Tamil Nadu | B46: 1109
A47: Telangana | B47: 906
A48: Uttar Pradesh | B48: 991
A49: West Bengal | B49: 665
A50: Grand Total | B50: 10000

Sheet Amazon _Sales_dashboard
T5: Return Rate %
T6: 0.05
